mipsy_macro/__init__.py
mipsy_macro/cli.py
mipsy_macro/macro.py
mipsy_macro/resources/reserved_words.json
mipsy_macro-0.2.0.dist-info/LICENSE
mipsy_macro-0.2.0.dist-info/METADATA
mipsy_macro-0.2.0.dist-info/WHEEL
mipsy_macro-0.2.0.dist-info/entry_points.txt
mipsy_macro-0.2.0.dist-info/top_level.txt
mipsy_macro-0.2.0.dist-info/RECORD
