Metadata-Version: 2.1
Name: mipsy_macro
Version: 0.2.0
Summary: A MIPS assembly macro preprocessor made for the mipsy emulator
License: GNU GENERAL PUBLIC LICENSE
Project-URL: Homepage, https://github.com/mcdcam/mipsy-macro
Classifier: Programming Language :: Python :: 3
Classifier: Operating System :: OS Independent
Classifier: License :: OSI Approved :: GNU General Public License v3 or later (GPLv3+)
Requires-Python: >=3.8
License-File: LICENSE
